{
  "shape0": {
    "periodic": false, 
    "knot": [
      0.0, 
      1.0, 
      2.0, 
      3.0, 
      4.0, 
      5.0, 
      6.0, 
      7.0, 
      8.0, 
      9.0, 
      10.0, 
      11.0, 
      12.0, 
      13.0, 
      14.0, 
      15.0, 
      16.0, 
      17.0, 
      18.0, 
      19.0, 
      20.0, 
      21.0, 
      22.0, 
      23.0, 
      24.0, 
      25.0, 
      26.0, 
      27.0, 
      28.0, 
      29.0, 
      30.0, 
      31.0, 
      32.0, 
      33.0, 
      34.0, 
      35.0, 
      36.0, 
      37.0, 
      38.0, 
      39.0, 
      40.0, 
      41.0, 
      42.0, 
      43.0, 
      44.0, 
      45.0, 
      46.0, 
      47.0, 
      48.0, 
      49.0, 
      50.0, 
      51.0, 
      52.0, 
      53.0, 
      54.0, 
      55.0, 
      56.0, 
      57.0, 
      58.0, 
      59.0, 
      60.0
    ], 
    "degree": 1, 
    "point": [
      [
        [
          33, 
          "cv[33]", 
          [
            33
          ]
        ], 
        [
          -0.8123654172854939, 
          5.489498687994821e-10, 
          -0.5902182885439182
        ]
      ], 
      [
        [
          16, 
          "cv[16]", 
          [
            16
          ]
        ], 
        [
          -0.3102960818840136, 
          5.489498687994821e-10, 
          0.954992740219764
        ]
      ], 
      [
        [
          53, 
          "cv[53]", 
          [
            53
          ]
        ], 
        [
          0.5902179043975687, 
          -0.8123652246633697, 
          -5.489498687994821e-10
        ]
      ], 
      [
        [
          12, 
          "cv[12]", 
          [
            12
          ]
        ], 
        [
          0.8123652246633697, 
          5.489498687994821e-10, 
          0.5902179043975687
        ]
      ], 
      [
        [
          14, 
          "cv[14]", 
          [
            14
          ]
        ], 
        [
          0.31029584138083316, 
          5.489498687994821e-10, 
          0.954992740219764
        ]
      ], 
      [
        [
          45, 
          "cv[45]", 
          [
            45
          ]
        ], 
        [
          -5.489498687994821e-10, 
          -2.2389350094361299e-07, 
          -1.004139102281416
        ]
      ], 
      [
        [
          31, 
          "cv[31]", 
          [
            31
          ]
        ], 
        [
          -0.3102958185382049, 
          5.489498687994821e-10, 
          -0.9549930286040013
        ]
      ], 
      [
        [
          10, 
          "cv[10]", 
          [
            10
          ]
        ], 
        [
          1.0041385266108411, 
          5.489498687994821e-10, 
          -5.489498687994821e-10
        ]
      ], 
      [
        [
          41, 
          "cv[41]", 
          [
            41
          ]
        ], 
        [
          -5.489498687994821e-10, 
          -0.9549932190303265, 
          -0.310295842478733
        ]
      ], 
      [
        [
          28, 
          "cv[28]", 
          [
            28
          ]
        ], 
        [
          -5.489498687994821e-10, 
          0.5902179054954677, 
          -0.812365704571831
        ]
      ], 
      [
        [
          47, 
          "cv[47]", 
          [
            47
          ]
        ], 
        [
          0.5902183832081304, 
          5.489498687994821e-10, 
          -0.8123655130476071
        ]
      ], 
      [
        [
          51, 
          "cv[51]", 
          [
            51
          ]
        ], 
        [
          0.954992740219764, 
          -0.31029584138083316, 
          -5.489498687994821e-10
        ]
      ], 
      [
        [
          43, 
          "cv[43]", 
          [
            43
          ]
        ], 
        [
          -5.489498687994821e-10, 
          -0.5902183832081304, 
          -0.8123655130476071
        ]
      ], 
      [
        [
          26, 
          "cv[26]", 
          [
            26
          ]
        ], 
        [
          -5.489498687994821e-10, 
          0.9549928370797759, 
          -0.3102961776461257
        ]
      ], 
      [
        [
          55, 
          "cv[55]", 
          [
            55
          ]
        ], 
        [
          -5.489496458359397e-10, 
          -1.0041385266108411, 
          -5.489498687994821e-10
        ]
      ], 
      [
        [
          57, 
          "cv[57]", 
          [
            57
          ]
        ], 
        [
          -5.489498687994821e-10, 
          -0.8123652246633697, 
          0.5902179043975687
        ]
      ], 
      [
        [
          34, 
          "cv[34]", 
          [
            34
          ]
        ], 
        [
          -0.9549928370797759, 
          5.489498687994821e-10, 
          -0.3102961776461257
        ]
      ], 
      [
        [
          23, 
          "cv[23]", 
          [
            23
          ]
        ], 
        [
          -0.5902182885439182, 
          0.8123654172854939, 
          -5.489498687994821e-10
        ]
      ], 
      [
        [
          25, 
          "cv[25]", 
          [
            25
          ]
        ], 
        [
          -1.6514008046456844e-07, 
          1.0041389107571903, 
          -5.489498687994821e-10
        ]
      ], 
      [
        [
          37, 
          "cv[37]", 
          [
            37
          ]
        ], 
        [
          -0.8123655130476071, 
          -0.5902183832081304, 
          -5.489498687994821e-10
        ]
      ], 
      [
        [
          21, 
          "cv[21]", 
          [
            21
          ]
        ], 
        [
          -0.9549930286040013, 
          0.3102958185382049, 
          -5.489498687994821e-10
        ]
      ], 
      [
        [
          19, 
          "cv[19]", 
          [
            19
          ]
        ], 
        [
          -0.9549928370797759, 
          5.489498687994821e-10, 
          0.3102958174403051
        ]
      ], 
      [
        [
          5, 
          "cv[5]", 
          [
            5
          ]
        ], 
        [
          -5.489498687994821e-10, 
          1.0041389107571903, 
          -1.6514008046456844e-07
        ]
      ], 
      [
        [
          1, 
          "cv[1]", 
          [
            1
          ]
        ], 
        [
          -5.489498687994821e-10, 
          0.3102960818840136, 
          0.954992740219764
        ]
      ], 
      [
        [
          7, 
          "cv[7]", 
          [
            7
          ]
        ], 
        [
          0.5902178565165129, 
          0.8123655130476071, 
          -5.489498687994821e-10
        ]
      ], 
      [
        [
          60, 
          "cv[60]", 
          [
            60
          ]
        ], 
        [
          -5.489498687994821e-10, 
          1.0528876024792537e-07, 
          1.0041387181350658
        ]
      ], 
      [
        [
          49, 
          "cv[49]", 
          [
            49
          ]
        ], 
        [
          0.9549932190303265, 
          5.489498687994821e-10, 
          -0.310295842478733
        ]
      ], 
      [
        [
          3, 
          "cv[3]", 
          [
            3
          ]
        ], 
        [
          -5.489498687994821e-10, 
          0.8123655130476071, 
          0.5902178565165129
        ]
      ], 
      [
        [
          38, 
          "cv[38]", 
          [
            38
          ]
        ], 
        [
          -0.5902180012575804, 
          -0.812365799236044, 
          -5.489498687994821e-10
        ]
      ], 
      [
        [
          59, 
          "cv[59]", 
          [
            59
          ]
        ], 
        [
          -5.489498687994821e-10, 
          -0.31029584138083316, 
          0.954992740219764
        ]
      ], 
      [
        [
          17, 
          "cv[17]", 
          [
            17
          ]
        ], 
        [
          -0.590218097019693, 
          5.489498687994821e-10, 
          0.8123652246633697
        ]
      ], 
      [
        [
          48, 
          "cv[48]", 
          [
            48
          ]
        ], 
        [
          0.812365799236044, 
          5.489498687994821e-10, 
          -0.5902180012575804
        ]
      ], 
      [
        [
          44, 
          "cv[44]", 
          [
            44
          ]
        ], 
        [
          -5.489498687994821e-10, 
          -0.3102962962508671, 
          -0.9549930286040013
        ]
      ], 
      [
        [
          9, 
          "cv[9]", 
          [
            9
          ]
        ], 
        [
          0.954992740219764, 
          0.3102960818840136, 
          -5.489498687994821e-10
        ]
      ], 
      [
        [
          52, 
          "cv[52]", 
          [
            52
          ]
        ], 
        [
          0.8123654161875938, 
          -0.5902178565165129, 
          -5.489498687994821e-10
        ]
      ], 
      [
        [
          15, 
          "cv[15]", 
          [
            15
          ]
        ], 
        [
          -5.489498687994821e-10, 
          1.0528876024792537e-07, 
          1.0041387181350658
        ]
      ], 
      [
        [
          29, 
          "cv[29]", 
          [
            29
          ]
        ], 
        [
          -5.489498687994821e-10, 
          0.3102958185382049, 
          -0.9549930286040013
        ]
      ], 
      [
        [
          56, 
          "cv[56]", 
          [
            56
          ]
        ], 
        [
          -5.489498687994821e-10, 
          -0.9549925486955405, 
          0.31029591320241745
        ]
      ], 
      [
        [
          11, 
          "cv[11]", 
          [
            11
          ]
        ], 
        [
          0.9549925486955405, 
          5.489498687994821e-10, 
          0.31029591320241745
        ]
      ], 
      [
        [
          50, 
          "cv[50]", 
          [
            50
          ]
        ], 
        [
          1.0041385266108411, 
          5.489498687994821e-10, 
          -5.489498687994821e-10
        ]
      ], 
      [
        [
          13, 
          "cv[13]", 
          [
            13
          ]
        ], 
        [
          0.5902178565165129, 
          5.489498687994821e-10, 
          0.8123654161875938
        ]
      ], 
      [
        [
          46, 
          "cv[46]", 
          [
            46
          ]
        ], 
        [
          0.3102962962508671, 
          5.489498687994821e-10, 
          -0.9549930286040013
        ]
      ], 
      [
        [
          54, 
          "cv[54]", 
          [
            54
          ]
        ], 
        [
          0.31029591320241745, 
          -0.9549925486955405, 
          -5.489498687994821e-10
        ]
      ], 
      [
        [
          35, 
          "cv[35]", 
          [
            35
          ]
        ], 
        [
          -1.0041389107571903, 
          5.489498687994821e-10, 
          -1.6514008046456844e-07
        ]
      ], 
      [
        [
          42, 
          "cv[42]", 
          [
            42
          ]
        ], 
        [
          -5.489498687994821e-10, 
          -0.812365799236044, 
          -0.5902180012575804
        ]
      ], 
      [
        [
          40, 
          "cv[40]", 
          [
            40
          ]
        ], 
        [
          -5.489498687994821e-10, 
          -1.0041385266108411, 
          -5.489498687994821e-10
        ]
      ], 
      [
        [
          27, 
          "cv[27]", 
          [
            27
          ]
        ], 
        [
          -5.489498687994821e-10, 
          0.8123654172854939, 
          -0.5902182885439182
        ]
      ], 
      [
        [
          30, 
          "cv[30]", 
          [
            30
          ]
        ], 
        [
          2.2389350094361299e-07, 
          5.489498687994821e-10, 
          -1.004139102281416
        ]
      ], 
      [
        [
          36, 
          "cv[36]", 
          [
            36
          ]
        ], 
        [
          -0.9549930286040013, 
          -0.3102962962508671, 
          -5.489498687994821e-10
        ]
      ], 
      [
        [
          8, 
          "cv[8]", 
          [
            8
          ]
        ], 
        [
          0.8123652246633697, 
          0.590218097019693, 
          -5.489498687994821e-10
        ]
      ], 
      [
        [
          24, 
          "cv[24]", 
          [
            24
          ]
        ], 
        [
          -0.3102961776461257, 
          0.9549928370797759, 
          -5.489498687994821e-10
        ]
      ], 
      [
        [
          18, 
          "cv[18]", 
          [
            18
          ]
        ], 
        [
          -0.8123655130476071, 
          5.489498687994821e-10, 
          0.5902178565165129
        ]
      ], 
      [
        [
          4, 
          "cv[4]", 
          [
            4
          ]
        ], 
        [
          -5.489498687994821e-10, 
          0.9549928370797759, 
          0.3102958174403051
        ]
      ], 
      [
        [
          20, 
          "cv[20]", 
          [
            20
          ]
        ], 
        [
          -1.0041389107571903, 
          5.489498687994821e-10, 
          -1.6514008046456844e-07
        ]
      ], 
      [
        [
          22, 
          "cv[22]", 
          [
            22
          ]
        ], 
        [
          -0.812365704571831, 
          0.5902179054954677, 
          -5.489498687994821e-10
        ]
      ], 
      [
        [
          32, 
          "cv[32]", 
          [
            32
          ]
        ], 
        [
          -0.5902179054954677, 
          5.489498687994821e-10, 
          -0.812365704571831
        ]
      ], 
      [
        [
          6, 
          "cv[6]", 
          [
            6
          ]
        ], 
        [
          0.3102958174403051, 
          0.9549928370797759, 
          -5.489498687994821e-10
        ]
      ], 
      [
        [
          2, 
          "cv[2]", 
          [
            2
          ]
        ], 
        [
          -5.489498687994821e-10, 
          0.590218097019693, 
          0.8123652246633697
        ]
      ], 
      [
        [
          58, 
          "cv[58]", 
          [
            58
          ]
        ], 
        [
          -5.489498687994821e-10, 
          -0.5902178565165129, 
          0.8123654161875938
        ]
      ], 
      [
        [
          0, 
          "cv[0]", 
          [
            0
          ]
        ], 
        [
          -5.489498687994821e-10, 
          1.0528876024792537e-07, 
          1.0041387181350658
        ]
      ], 
      [
        [
          39, 
          "cv[39]", 
          [
            39
          ]
        ], 
        [
          -0.310295842478733, 
          -0.9549932190303265, 
          -5.489498687994821e-10
        ]
      ]
    ]
  }
}